x_browser_client/__init__.py
x_browser_client/cli.py
x_browser_client/config.py
x_browser_client/data_types.py
x_browser_client/x.py
x_browser_client-0.1.0.dist-info/METADATA
x_browser_client-0.1.0.dist-info/WHEEL
x_browser_client-0.1.0.dist-info/entry_points.txt
x_browser_client-0.1.0.dist-info/top_level.txt
x_browser_client-0.1.0.dist-info/RECORD
