Metadata-Version: 2.2
Name: x_browser_client
Version: 0.1.0
Summary: A Python package for interacting with X.com using Playwright-powered automation. Meant for use with AI agents. Requires a windowed environment, optimally Ubuntu or Windows.
Home-page: https://github.com/laelhalawani/x_browser_client
Author: Lael Al-Halawani
Author-email: laelhalawani@gmail.com
Classifier: Programming Language :: Python :: 3
Classifier: License :: OSI Approved :: MIT License
Classifier: Operating System :: OS Independent
Classifier: Intended Audience :: Developers
Classifier: Topic :: Software Development :: Libraries :: Python Modules
Requires-Python: >=3.11
Requires-Dist: playwright
Requires-Dist: beautifulsoup4
Requires-Dist: openai
Requires-Dist: pytest
Requires-Dist: python-dotenv
Dynamic: author
Dynamic: author-email
Dynamic: classifier
Dynamic: description
Dynamic: description-content-type
Dynamic: home-page
Dynamic: requires-dist
Dynamic: requires-python
Dynamic: summary
